__init__.py
__main__.py
main.py
qr_core.py
pysimpleqr-0.1.2.dist-info/METADATA
pysimpleqr-0.1.2.dist-info/WHEEL
pysimpleqr-0.1.2.dist-info/entry_points.txt
pysimpleqr-0.1.2.dist-info/top_level.txt
pysimpleqr-0.1.2.dist-info/RECORD
