Metadata-Version: 2.4
Name: pysimpleqr
Version: 0.1.2
Summary: use qr to transit messages from OS to other devices, e.g. handset
Project-URL: Homepage, https://github.com/fxyzbtc/pysimpleqr
Project-URL: Repository, https://github.com/fxyzbtc/pysimpleqr
Keywords: qr,qrcode,simpleqr
Classifier: Programming Language :: Python :: 3
Classifier: Operating System :: OS Independent
Classifier: Topic :: Utilities
Requires-Python: >=3.12
Requires-Dist: loguru>=0.7.3
Requires-Dist: tqdm>=4.67.1
Requires-Dist: typer>=0.12.5
Requires-Dist: pysimplegui>=5.0.7
Requires-Dist: Pillow>=11.0.0
Requires-Dist: qrcode[pil]>=7.4.2
Requires-Dist: pyperclip>=1.9.0
Provides-Extra: windows
Requires-Dist: pywin32>=306; extra == "windows"
